{
  "id": "assignments",
  "title": "Assignments (Per Game/Env Function Sets)",
  "description": "This document describes a minimal control-plane for function assignments per game/env. It is an early building block for M5 (pack downlink & hot update).",
  "source": "@site/docs/assignments.md",
  "sourceDirName": ".",
  "slug": "/assignments",
  "permalink": "/croupier/assignments",
  "draft": false,
  "unlisted": false,
  "editUrl": "https://github.com/cuihairu/croupier/edit/main/docs/docs/assignments.md",
  "tags": [],
  "version": "current",
  "lastUpdatedBy": null,
  "lastUpdatedAt": null,
  "frontMatter": {},
  "sidebar": "docs",
  "previous": {
    "title": "API",
    "permalink": "/croupier/api"
  },
  "next": {
    "title": "完整游戏团队角色权限体系设计",
    "permalink": "/croupier/complete-game-roles-design"
  }
}